catelier.cpython-310-powerpc64le-linux-gnu.so
catelier-1.0.1.dist-info/top_level.txt
catelier-1.0.1.dist-info/RECORD
catelier-1.0.1.dist-info/LICENSE
catelier-1.0.1.dist-info/METADATA
catelier-1.0.1.dist-info/WHEEL
